{
  "displayName": "VNX",
  "puzzles": {
    "intro": {
      "puzName": "intro",
      "slug": "a_night_under_the_stars",
      "displayName": "A Night Under The Stars",
      "isNew": true,
      "unlockTime": 1726916399927,
      "solveTime": 1726916454930,
      "isStory": true,
      "mapPos": {
        "x": 86.65771484375,
        "y": 23.6358642578125
      },
      "cutsceneImages": [
        "intro.svg",
        "intro-ok.svg",
        "blank",
        "starry-sky",
        "blank-sky",
        "falling-star",
        "falling-stelle",
        "stelle-collapsed",
        "stelle",
        "stelle-thinking"
      ],
      "noCannedHints": true
    },
    "puz49": {
      "puzName": "puz49",
      "slug": "towers_i",
      "displayName": "Towers I",
      "hasAnswer": true,
      "answer": "AMALGAMATE",
      "isNew": true,
      "unlockTime": 1726916458770,
      "solveTime": 1726917370134,
      "sequenceId": "towers",
      "constellationEdges": [
        "puz28"
      ],
      "mapPos": {
        "x": 17,
        "y": 15
      }
    },
    "first-wish": {
      "puzName": "first-wish",
      "slug": "a_fallen_star",
      "displayName": "A Fallen Star",
      "isNew": true,
      "unlockTime": 1726916458772,
      "solveTime": 1726917215319,
      "isStory": true,
      "mapPos": {
        "x": 76.165771484375,
        "y": 36.048126220703125
      },
      "cutsceneImages": [
        "stelle-thinking",
        "stelle",
        "stelle-happy"
      ],
      "noCannedHints": true
    },
    "puz199": {
      "puzName": "puz199",
      "slug": "fdc12c7a",
      "displayName": "ᓇᓇᓇᓇᓇᓇᓇᓇᓇᓇᓇᓇᓇ",
      "hasAnswer": true,
      "answer": "BATMAN",
      "isNew": true,
      "unlockTime": 1726916463467,
      "solveTime": 1726919050317,
      "sequenceId": "na",
      "constellationEdges": [
        "puz204"
      ],
      "mapPos": {
        "x": 82,
        "y": 22
      }
    },
    "puz255": {
      "puzName": "puz255",
      "slug": "shakashakari",
      "displayName": "Shakashakari",
      "hasAnswer": true,
      "answer": "SHINING",
      "isNew": true,
      "unlockTime": 1726916465924,
      "solveTime": 1727076650382,
      "mapPos": {
        "x": 1.72271728515625,
        "y": 0.22430419921875
      },
      "hasMultipleAnswers": true
    },
    "puz62": {
      "puzName": "puz62",
      "slug": "half_mile_grid",
      "displayName": "Half Mile Grid",
      "hasAnswer": true,
      "isNew": true,
      "unlockTime": 1726916468366,
      "mapPos": {
        "x": 35.49346923828125,
        "y": 27.355194091796875
      }
    },
    "puz232": {
      "puzName": "puz232",
      "slug": "mobel",
      "displayName": "Möbel",
      "hasAnswer": true,
      "answer": "BANK",
      "isNew": true,
      "unlockTime": 1726916470541,
      "solveTime": 1726963470706,
      "sequenceId": "sweden",
      "constellationEdges": [
        "puz235"
      ],
      "mapPos": {
        "x": 92,
        "y": 41
      }
    },
    "first-solve": {
      "puzName": "first-solve",
      "slug": "a_glimmer_of_hope",
      "displayName": "A Glimmer of Hope",
      "isNew": true,
      "unlockTime": 1726917370135,
      "solveTime": 1726917519026,
      "isStory": true,
      "mapPos": {
        "x": 1.129150390625,
        "y": 9.30328369140625
      },
      "cutsceneImages": [
        "stelle",
        "stelle-happy",
        "stelle-thinking"
      ],
      "noCannedHints": true
    },
    "puz82": {
      "puzName": "puz82",
      "slug": "af47cd28",
      "displayName": "读。听。",
      "hasAnswer": true,
      "answer": "CODE",
      "isNew": true,
      "unlockTime": 1726917382100,
      "solveTime": 1726917556930,
      "mapPos": {
        "x": 74.70245361328125,
        "y": 2.457427978515625
      }
    },
    "puz64": {
      "puzName": "puz64",
      "slug": "ancient_greek_numbers",
      "displayName": "Ancient Greek numbers",
      "hasAnswer": true,
      "answer": "PHOENIX",
      "isNew": true,
      "unlockTime": 1726917568863,
      "solveTime": 1726917596620,
      "sequenceId": "greek",
      "constellationEdges": [
        "puz65"
      ],
      "mapPos": {
        "x": 72,
        "y": 39
      }
    },
    "puz108": {
      "puzName": "puz108",
      "slug": "cro_ssw_ord",
      "displayName": "CRO/SSW/ORD",
      "hasAnswer": true,
      "answer": "PEASANTRY",
      "isNew": true,
      "unlockTime": 1726917600508,
      "solveTime": 1726917609899,
      "sequenceId": "crossword",
      "constellationEdges": [
        "puz298"
      ],
      "mapPos": {
        "x": 33,
        "y": 16
      }
    },
    "puz259": {
      "puzName": "puz259",
      "slug": "espresso",
      "displayName": "Espresso",
      "hasAnswer": true,
      "answer": "EMPIRE",
      "isNew": true,
      "unlockTime": 1726917613228,
      "solveTime": 1726963873122,
      "sequenceId": "espresso",
      "constellationEdges": [
        "puz267"
      ],
      "mapPos": {
        "x": 37,
        "y": 24
      }
    },
    "puz23": {
      "puzName": "puz23",
      "slug": "nyc_subway",
      "displayName": "NYC Subway",
      "hasAnswer": true,
      "answer": "GRAND SLAM",
      "isNew": true,
      "unlockTime": 1726917664758,
      "solveTime": 1726918033886,
      "mapPos": {
        "x": 30.1910400390625,
        "y": 15.5609130859375
      }
    },
    "brighter-skies": {
      "puzName": "brighter-skies",
      "slug": "brighter_skies",
      "displayName": "Brighter Skies",
      "isNew": true,
      "unlockTime": 1726918033887,
      "isStory": true,
      "mapPos": {
        "x": 12.48016357421875,
        "y": 25.244903564453125
      },
      "cutsceneImages": [
        "stelle",
        "stelle-happy",
        "stelle-thinking"
      ],
      "noCannedHints": true
    },
    "puz268": {
      "puzName": "puz268",
      "slug": "necklace",
      "displayName": "Necklace",
      "hasAnswer": true,
      "answer": "ORIENTAL PEARL TOWER",
      "isNew": true,
      "unlockTime": 1726918038832,
      "solveTime": 1726966479240,
      "sequenceId": "necklace",
      "constellationEdges": [
        "puz272"
      ],
      "mapPos": {
        "x": 86,
        "y": 46
      }
    },
    "puz69": {
      "puzName": "puz69",
      "slug": "f3f9420a",
      "displayName": "",
      "hasAnswer": true,
      "isNew": true,
      "unlockTime": 1726919056103,
      "rarity": "epic",
      "mapPos": {
        "x": 82.7728271484375,
        "y": 31.78253173828125
      },
      "untitledPuzzleIndex": 0
    },
    "puz265": {
      "puzName": "puz265",
      "slug": "470904ae",
      "displayName": "",
      "hasAnswer": true,
      "answer": "MYOBLAST",
      "isNew": true,
      "unlockTime": 1726919717851,
      "solveTime": 1727061368567,
      "sequenceId": "espresso",
      "mapPos": {
        "x": 36.9,
        "y": 35.3
      },
      "untitledPuzzleIndex": 1
    },
    "puz104": {
      "puzName": "puz104",
      "slug": "8effef7c",
      "displayName": "",
      "hasAnswer": true,
      "answer": "LODGE",
      "isNew": true,
      "unlockTime": 1726923378294,
      "solveTime": 1727451014503,
      "rarity": "rare",
      "mapPos": {
        "x": 60.5377197265625,
        "y": 2.288055419921875
      },
      "untitledPuzzleIndex": 2
    },
    "puz247": {
      "puzName": "puz247",
      "slug": "matchups",
      "displayName": "Matchups",
      "hasAnswer": true,
      "answer": "CHART",
      "isNew": true,
      "unlockTime": 1726963477871,
      "solveTime": 1727451066122,
      "rarity": "uncommon",
      "mapPos": {
        "x": 44.09027099609375,
        "y": 43.502044677734375
      }
    },
    "puz221": {
      "puzName": "puz221",
      "slug": "468a6325",
      "displayName": "",
      "hasAnswer": true,
      "isNew": true,
      "unlockTime": 1726963876961,
      "mapPos": {
        "x": 81.640625,
        "y": 40.069580078125
      },
      "untitledPuzzleIndex": 3
    },
    "puz141": {
      "puzName": "puz141",
      "slug": "domino_effect",
      "displayName": "Domino Effect",
      "hasAnswer": true,
      "answer": "GRID",
      "isNew": true,
      "unlockTime": 1726966484296,
      "solveTime": 1727070738658,
      "sequenceId": "domino",
      "constellationEdges": [
        "puz132"
      ],
      "rarity": "uncommon",
      "mapPos": {
        "x": 73,
        "y": 8
      }
    },
    "puz13": {
      "puzName": "puz13",
      "slug": "never_will_i_ever",
      "displayName": "Never Will I Ever",
      "hasAnswer": true,
      "isNew": true,
      "unlockTime": 1727025282132,
      "mapPos": {
        "x": 7.550048828125,
        "y": 42.789459228515625
      }
    },
    "puz237": {
      "puzName": "puz237",
      "slug": "picturegame",
      "displayName": "PictureGame",
      "hasAnswer": true,
      "answerNormalization": "uppercase_letters_or_symbols_only",
      "isNew": true,
      "unlockTime": 1727070760912,
      "rarity": "uncommon",
      "mapPos": {
        "x": 75.62103271484375,
        "y": 19.676971435546875
      }
    },
    "puz54": {
      "puzName": "puz54",
      "slug": "strong_greek_numbers",
      "displayName": "Strong Greek numbers",
      "hasAnswer": true,
      "answer": "COMPLEX",
      "isNew": true,
      "unlockTime": 1727076653586,
      "solveTime": 1727076688632,
      "sequenceId": "greek",
      "constellationEdges": [
        "puz64"
      ],
      "mapPos": {
        "x": 71,
        "y": 44
      }
    },
    "puz107": {
      "puzName": "puz107",
      "slug": "make_your_own_crossword_puzzle",
      "displayName": "Make Your Own Crossword Puzzle",
      "hasAnswer": true,
      "isNew": true,
      "unlockTime": 1727081200482,
      "rarity": "epic",
      "mapPos": {
        "x": 62.34283447265625,
        "y": 18.44940185546875
      }
    },
    "puz80": {
      "puzName": "puz80",
      "slug": "festive_greek_numbers",
      "displayName": "Festive Greek numbers",
      "hasAnswer": true,
      "answer": "DOGPILE",
      "isNew": true,
      "unlockTime": 1727123331964,
      "solveTime": 1727123355716,
      "sequenceId": "greek",
      "rarity": "uncommon",
      "mapPos": {
        "x": 75,
        "y": 38
      }
    },
    "puz132": {
      "puzName": "puz132",
      "slug": "make_3x5",
      "displayName": "Make 3×5",
      "hasAnswer": true,
      "answer": "TULIP",
      "isNew": true,
      "unlockTime": 1727123381581,
      "solveTime": 1727140370983,
      "sequenceId": "domino",
      "rarity": "rare",
      "mapPos": {
        "x": 72,
        "y": 4
      }
    },
    "puz21": {
      "puzName": "puz21",
      "slug": "i_had_a_united_states_television",
      "displayName": "I HAD A UNITED STATES TELEVISION",
      "hasAnswer": true,
      "answer": "UNDERSCORE",
      "isNew": true,
      "unlockTime": 1727140393176,
      "solveTime": 1727140402722,
      "sequenceId": "jfk",
      "constellationEdges": [
        "puz171"
      ],
      "mapPos": {
        "x": 78,
        "y": 36
      }
    },
    "puz285": {
      "puzName": "puz285",
      "slug": "five_by_five_dbf69e59",
      "displayName": "Five-By-Five",
      "hasAnswer": true,
      "answer": "LANAI",
      "isNew": true,
      "unlockTime": 1727140404723,
      "solveTime": 1727216398909,
      "sequenceId": "five",
      "constellationEdges": [
        "puz286"
      ],
      "mapPos": {
        "x": 62.5,
        "y": 32.6
      }
    },
    "puz157": {
      "puzName": "puz157",
      "slug": "clues",
      "displayName": "Clues",
      "hasAnswer": true,
      "answer": "CHAIN",
      "isNew": true,
      "unlockTime": 1727216414185,
      "solveTime": 1727216445318,
      "mapPos": {
        "x": 83.2794189453125,
        "y": 38.941192626953125
      }
    },
    "puz41": {
      "puzName": "puz41",
      "slug": "high_precision",
      "displayName": "High Precision",
      "hasAnswer": true,
      "answer": "PAIGE",
      "isNew": true,
      "unlockTime": 1727216462864,
      "solveTime": 1727216471240,
      "rarity": "uncommon",
      "mapPos": {
        "x": 61.8011474609375,
        "y": 49.964141845703125
      }
    },
    "puz168": {
      "puzName": "puz168",
      "slug": "and_if_you_look_to_the_right",
      "displayName": "And if you look to the right...",
      "hasAnswer": true,
      "answer": "MOUNT RAINIER",
      "isNew": true,
      "unlockTime": 1727216478847,
      "solveTime": 1727216490019,
      "sequenceId": "look",
      "constellationEdges": [
        "puz170"
      ],
      "mapPos": {
        "x": 79,
        "y": 2
      }
    },
    "puz103": {
      "puzName": "puz103",
      "slug": "cc203922",
      "displayName": "",
      "hasAnswer": true,
      "answer": "SWIMMING",
      "isNew": true,
      "unlockTime": 1727216491698,
      "solveTime": 1727216501652,
      "mapPos": {
        "x": 26.2359619140625,
        "y": 30.037689208984375
      },
      "untitledPuzzleIndex": 4
    },
    "puz250": {
      "puzName": "puz250",
      "slug": "path",
      "displayName": "Path",
      "hasAnswer": true,
      "answer": "AMOGUS",
      "isNew": true,
      "unlockTime": 1727247041693,
      "solveTime": 1727451048742,
      "sequenceId": "wikipedia",
      "constellationEdges": [
        "puz117"
      ],
      "mapPos": {
        "x": 32,
        "y": 24
      }
    },
    "puz251": {
      "puzName": "puz251",
      "slug": "not_loss",
      "displayName": "Not Loss",
      "hasAnswer": true,
      "isNew": true,
      "unlockTime": 1727247527761,
      "rarity": "epic",
      "mapPos": {
        "x": 5.29327392578125,
        "y": 32.30133056640625
      }
    },
    "puz183": {
      "puzName": "puz183",
      "slug": "data_visualization",
      "displayName": "Data visualization",
      "hasAnswer": true,
      "answer": "GAIN",
      "isNew": true,
      "unlockTime": 1727439001254,
      "solveTime": 1727451060126,
      "mapPos": {
        "x": 15.18402099609375,
        "y": 11.8438720703125
      }
    },
    "puz114": {
      "puzName": "puz114",
      "slug": "6feaa304",
      "displayName": "",
      "hasAnswer": true,
      "answer": "CODER",
      "isNew": true,
      "unlockTime": 1727451078404,
      "solveTime": 1727451110435,
      "rarity": "uncommon",
      "mapPos": {
        "x": 9.86785888671875,
        "y": 6.30950927734375
      },
      "untitledPuzzleIndex": 5
    },
    "puz97": {
      "puzName": "puz97",
      "slug": "morse_code",
      "displayName": "Morse Code",
      "hasAnswer": true,
      "answerNormalization": "uppercase_letters_or_symbols_only",
      "isNew": true,
      "unlockTime": 1727451112826,
      "rarity": "uncommon",
      "mapPos": {
        "x": 57.33184814453125,
        "y": 8.43658447265625
      }
    },
    "puz146": {
      "puzName": "puz146",
      "slug": "despair",
      "displayName": "Despair",
      "hasAnswer": true,
      "answer": "DESPISED",
      "isNew": true,
      "unlockTime": 1727451123240,
      "solveTime": 1727451131842,
      "sequenceId": "despair",
      "constellationEdges": [
        "puz189"
      ],
      "mapPos": {
        "x": 33,
        "y": 46
      }
    },
    "puz235": {
      "puzName": "puz235",
      "slug": "the_system",
      "displayName": "The System",
      "hasAnswer": true,
      "answer": "NOVA",
      "isNew": true,
      "unlockTime": 1727451131841,
      "solveTime": 1727451230312,
      "sequenceId": "sweden",
      "mapPos": {
        "x": 93,
        "y": 38
      }
    },
    "puz28": {
      "puzName": "puz28",
      "slug": "towers_ii",
      "displayName": "Towers II",
      "hasAnswer": true,
      "answer": "ABRACADABRA",
      "isNew": true,
      "unlockTime": 1727451136605,
      "solveTime": 1727451157540,
      "sequenceId": "towers",
      "constellationEdges": [
        "puz25"
      ],
      "mapPos": {
        "x": 18,
        "y": 12
      }
    },
    "puz86": {
      "puzName": "puz86",
      "slug": "b4e58ab3",
      "displayName": "",
      "hasAnswer": true,
      "isNew": true,
      "unlockTime": 1727451159510,
      "mapPos": {
        "x": 2.4139404296875,
        "y": 42.19818115234375
      },
      "untitledPuzzleIndex": 6
    },
    "puz274": {
      "puzName": "puz274",
      "slug": "md5",
      "displayName": "md5...?.....?.?....?.......?....",
      "hasAnswer": true,
      "isNew": true,
      "unlockTime": 1727451243684,
      "mapPos": {
        "x": 75.4425048828125,
        "y": 23.2879638671875
      }
    },
    "puz94": {
      "puzName": "puz94",
      "slug": "1a91dc59",
      "displayName": "",
      "hasAnswer": true,
      "answer": "MOVEMENT",
      "isNew": true,
      "unlockTime": 1727451249220,
      "solveTime": 1727451261966,
      "rarity": "rare",
      "mapPos": {
        "x": 95.513916015625,
        "y": 43.631744384765625
      },
      "untitledPuzzleIndex": 7
    },
    "puz313": {
      "puzName": "puz313",
      "slug": "the_hope_pool",
      "displayName": "The Hope Pool",
      "isNew": true,
      "unlockTime": 1727451269171,
      "mapPos": {
        "x": 76.49078369140625,
        "y": 31.137847900390625
      },
      "noCannedHints": true
    },
    "puz171": {
      "puzName": "puz171",
      "slug": "bro_seas_teas_as_so_so",
      "displayName": "BRO SEAS TEAS AS SO SO",
      "hasAnswer": true,
      "answer": "POLONIUM",
      "isNew": true,
      "unlockTime": 1727451298742,
      "solveTime": 1727451320546,
      "sequenceId": "jfk",
      "mapPos": {
        "x": 79,
        "y": 31
      }
    },
    "puz36": {
      "puzName": "puz36",
      "slug": "sums",
      "displayName": "Sums",
      "hasAnswer": true,
      "answer": "VECTORS",
      "isNew": true,
      "unlockTime": 1727451329451,
      "solveTime": 1727451340551,
      "rarity": "uncommon",
      "mapPos": {
        "x": 59.2041015625,
        "y": 18.183135986328125
      }
    }
  },
  "huntStartTime": 1726871280000,
  "huntEndTime": 1727735280000,
  "hopeSnapshot": {
    "hope": 5.002833333333488,
    "timestamp": 1727451628452
  },
  "cutsceneChoices": {},
  "lockedSolutions": {}
}