{
  "displayName": "SpaceCadets",
  "puzzles": {
    "intro": {
      "puzName": "intro",
      "slug": "a_night_under_the_stars",
      "displayName": "A Night Under The Stars",
      "isNew": true,
      "unlockTime": 1726873713435,
      "solveTime": 1726875515185,
      "isStory": true,
      "mapPos": {
        "x": 86.65771484375,
        "y": 23.6358642578125
      },
      "cutsceneImages": [
        "intro.svg",
        "intro-ok.svg",
        "blank",
        "starry-sky",
        "blank-sky",
        "falling-star",
        "falling-stelle",
        "stelle-collapsed",
        "stelle",
        "stelle-thinking"
      ],
      "noCannedHints": true
    },
    "puz232": {
      "puzName": "puz232",
      "slug": "mobel",
      "displayName": "Möbel",
      "hasAnswer": true,
      "answer": "BANK",
      "isNew": true,
      "unlockTime": 1726963204362,
      "solveTime": 1726983374738,
      "sequenceId": "sweden",
      "constellationEdges": [
        "puz235"
      ],
      "mapPos": {
        "x": 92,
        "y": 41
      }
    },
    "first-wish": {
      "puzName": "first-wish",
      "slug": "a_fallen_star",
      "displayName": "A Fallen Star",
      "isNew": true,
      "unlockTime": 1726963204364,
      "solveTime": 1726964179436,
      "isStory": true,
      "mapPos": {
        "x": 76.165771484375,
        "y": 36.048126220703125
      },
      "cutsceneImages": [
        "stelle-thinking",
        "stelle",
        "stelle-happy"
      ],
      "noCannedHints": true
    },
    "first-solve": {
      "puzName": "first-solve",
      "slug": "a_glimmer_of_hope",
      "displayName": "A Glimmer of Hope",
      "isNew": true,
      "unlockTime": 1726983374739,
      "solveTime": 1726992436394,
      "isStory": true,
      "mapPos": {
        "x": 1.129150390625,
        "y": 9.30328369140625
      },
      "cutsceneImages": [
        "stelle",
        "stelle-happy",
        "stelle-thinking"
      ],
      "noCannedHints": true
    },
    "puz120": {
      "puzName": "puz120",
      "slug": "bubble_wrap_puzzle",
      "displayName": "Bubble Wrap Puzzle",
      "hasAnswer": true,
      "answer": "WITHIN",
      "isNew": true,
      "unlockTime": 1726992444369,
      "solveTime": 1727421114303,
      "mapPos": {
        "x": 93.59588623046875,
        "y": 11.731719970703125
      }
    },
    "puz4": {
      "puzName": "puz4",
      "slug": "speech_of_the_officials",
      "displayName": "Speech of the Officials",
      "hasAnswer": true,
      "answer": "MISSING",
      "isNew": true,
      "unlockTime": 1726992697260,
      "solveTime": 1727088328680,
      "mapPos": {
        "x": 33.7005615234375,
        "y": 32.66754150390625
      }
    },
    "puz170": {
      "puzName": "puz170",
      "slug": "and_if_you_look_to_the_left",
      "displayName": "And if you look to the left...",
      "hasAnswer": true,
      "answer": "HIMEJI CASTLE",
      "isNew": true,
      "unlockTime": 1727077671660,
      "solveTime": 1727377830590,
      "sequenceId": "look",
      "mapPos": {
        "x": 82,
        "y": 4
      }
    },
    "puz142": {
      "puzName": "puz142",
      "slug": "spuejq",
      "displayName": "spueȷq",
      "hasAnswer": true,
      "answer": "DYSON",
      "isNew": true,
      "unlockTime": 1727086853970,
      "solveTime": 1727336294185,
      "mapPos": {
        "x": 48.50006103515625,
        "y": 14.91546630859375
      }
    },
    "puz53": {
      "puzName": "puz53",
      "slug": "obligatory_connections_puzzle",
      "displayName": "Obligatory Connections Puzzle",
      "hasAnswer": true,
      "answer": "SYZYGY",
      "isNew": true,
      "unlockTime": 1727088579191,
      "solveTime": 1727423298346,
      "mapPos": {
        "x": 33.02459716796875,
        "y": 32.315826416015625
      },
      "hasMultipleAnswers": true
    },
    "puz26": {
      "puzName": "puz26",
      "slug": "owo",
      "displayName": "owo",
      "hasAnswer": true,
      "answer": "AVOW",
      "isNew": true,
      "unlockTime": 1727243285592,
      "solveTime": 1727256835109,
      "mapPos": {
        "x": 57.34405517578125,
        "y": 18.47076416015625
      }
    },
    "puz38": {
      "puzName": "puz38",
      "slug": "lele",
      "displayName": "LELE!",
      "hasAnswer": true,
      "isNew": true,
      "unlockTime": 1727256858983,
      "mapPos": {
        "x": 83.27789306640625,
        "y": 48.55804443359375
      }
    },
    "puz67": {
      "puzName": "puz67",
      "slug": "extremely_easy_puzzle",
      "displayName": "Extremely Easy Puzzle",
      "hasAnswer": true,
      "answer": "ANSWER",
      "isNew": true,
      "unlockTime": 1727272854177,
      "solveTime": 1727307983082,
      "sequenceId": "difficulty",
      "constellationEdges": [
        "puz68"
      ],
      "mapPos": {
        "x": 40.3,
        "y": 14
      }
    },
    "puz108": {
      "puzName": "puz108",
      "slug": "cro_ssw_ord",
      "displayName": "CRO/SSW/ORD",
      "hasAnswer": true,
      "answer": "PEASANTRY",
      "isNew": true,
      "unlockTime": 1727308033252,
      "solveTime": 1727329073224,
      "sequenceId": "crossword",
      "constellationEdges": [
        "puz298"
      ],
      "mapPos": {
        "x": 33,
        "y": 16
      }
    },
    "brighter-skies": {
      "puzName": "brighter-skies",
      "slug": "brighter_skies",
      "displayName": "Brighter Skies",
      "isNew": true,
      "unlockTime": 1727329073225,
      "solveTime": 1727329153017,
      "isStory": true,
      "mapPos": {
        "x": 12.48016357421875,
        "y": 25.244903564453125
      },
      "cutsceneImages": [
        "stelle",
        "stelle-happy",
        "stelle-thinking"
      ],
      "noCannedHints": true
    },
    "puz69": {
      "puzName": "puz69",
      "slug": "f3f9420a",
      "displayName": "",
      "hasAnswer": true,
      "isNew": true,
      "unlockTime": 1727329725571,
      "rarity": "epic",
      "mapPos": {
        "x": 82.7728271484375,
        "y": 31.78253173828125
      },
      "untitledPuzzleIndex": 0
    },
    "puz6": {
      "puzName": "puz6",
      "slug": "three_crosses",
      "displayName": "Three Crosses",
      "hasAnswer": true,
      "isNew": true,
      "unlockTime": 1727331062279,
      "rarity": "uncommon",
      "mapPos": {
        "x": 60.55755615234375,
        "y": 40.908050537109375
      }
    },
    "puz112": {
      "puzName": "puz112",
      "slug": "redundancy",
      "displayName": "Redundancy",
      "hasAnswer": true,
      "isNew": true,
      "unlockTime": 1727332525012,
      "rarity": "uncommon",
      "mapPos": {
        "x": 30.53741455078125,
        "y": 43.18389892578125
      }
    },
    "puz269": {
      "puzName": "puz269",
      "slug": "numbers",
      "displayName": "Numbers",
      "hasAnswer": true,
      "isNew": true,
      "unlockTime": 1727335325354,
      "rarity": "uncommon",
      "mapPos": {
        "x": 94.38323974609375,
        "y": 37.7410888671875
      }
    },
    "puz64": {
      "puzName": "puz64",
      "slug": "ancient_greek_numbers",
      "displayName": "Ancient Greek numbers",
      "hasAnswer": true,
      "answer": "PHOENIX",
      "isNew": true,
      "unlockTime": 1727423404601,
      "solveTime": 1727492159032,
      "sequenceId": "greek",
      "constellationEdges": [
        "puz65"
      ],
      "mapPos": {
        "x": 72,
        "y": 39
      }
    },
    "puz298": {
      "puzName": "puz298",
      "slug": "c_r_o_s_s_w_o_r_d",
      "displayName": "C/R/O/S/S/W/O/R/D",
      "hasAnswer": true,
      "isNew": true,
      "unlockTime": 1727492165779,
      "sequenceId": "crossword",
      "constellationEdges": [
        "puz302"
      ],
      "mapPos": {
        "x": 34,
        "y": 13
      }
    },
    "puz279": {
      "puzName": "puz279",
      "slug": "actually_honestly_genuinely",
      "displayName": "Actually, honestly, genuinely quite mean",
      "hasAnswer": true,
      "isNew": true,
      "unlockTime": 1727498853984,
      "mapPos": {
        "x": 46.35772705078125,
        "y": 10.74371337890625
      }
    },
    "puz104": {
      "puzName": "puz104",
      "slug": "8effef7c",
      "displayName": "",
      "hasAnswer": true,
      "isNew": true,
      "unlockTime": 1727504870448,
      "rarity": "rare",
      "mapPos": {
        "x": 60.5377197265625,
        "y": 2.288055419921875
      },
      "untitledPuzzleIndex": 1
    }
  },
  "huntStartTime": 1726871280000,
  "huntEndTime": 1727735280000,
  "hopeSnapshot": {
    "hope": 900,
    "timestamp": 1727504870449
  },
  "cutsceneChoices": {},
  "lockedSolutions": {}
}